poetryaddbuttondriver/__init__.py
poetryaddbuttondriver/buttonDriver.py
poetryaddbuttondriver-0.1.0.dist-info/METADATA
poetryaddbuttondriver-0.1.0.dist-info/WHEEL
poetryaddbuttondriver-0.1.0.dist-info/RECORD
