Metadata-Version: 2.1
Name: poetryaddbuttondriver
Version: 0.1.0
Summary: 
Author: DPretorius
Author-email: dpretorius@csir.co.za
Requires-Python: >=3.11,<4.0
Classifier: Programming Language :: Python :: 3
Classifier: Programming Language :: Python :: 3.11
Classifier: Programming Language :: Python :: 3.12
Requires-Dist: pynput (==1.6.8)
